{
	"backtraceGraph" : 
	{
		"commands" : 
		[
			"install"
		],
		"files" : 
		[
			"CMakeLists.txt"
		],
		"nodes" : 
		[
			{
				"file" : 0
			},
			{
				"command" : 0,
				"file" : 0,
				"line" : 51,
				"parent" : 0
			},
			{
				"command" : 0,
				"file" : 0,
				"line" : 80,
				"parent" : 0
			},
			{
				"command" : 0,
				"file" : 0,
				"line" : 83,
				"parent" : 0
			},
			{
				"command" : 0,
				"file" : 0,
				"line" : 86,
				"parent" : 0
			},
			{
				"command" : 0,
				"file" : 0,
				"line" : 89,
				"parent" : 0
			}
		]
	},
	"installers" : 
	[
		{
			"backtrace" : 1,
			"component" : "Unspecified",
			"destination" : "include",
			"paths" : 
			[
				"zmq.hpp",
				"zmq_addon.hpp"
			],
			"type" : "file"
		},
		{
			"backtrace" : 2,
			"component" : "Unspecified",
			"destination" : "lib/pkgconfig",
			"paths" : 
			[
				"/home/carolina/Documentos/masters/1st_year/1st_semester/SDLE/project/g12/build/cppzmq.pc"
			],
			"type" : "file"
		},
		{
			"backtrace" : 3,
			"component" : "Unspecified",
			"destination" : "share/cmake/cppzmq",
			"exportName" : "cppzmq-targets",
			"exportTargets" : 
			[
				{
					"id" : "cppzmq::@6890427a1f51a3e7e1df",
					"index" : 0
				},
				{
					"id" : "cppzmq-static::@6890427a1f51a3e7e1df",
					"index" : 0
				}
			],
			"paths" : 
			[
				"CMakeFiles/Export/750a3790666afd90a690bdda5623fd1d/cppzmqTargets.cmake"
			],
			"type" : "export"
		},
		{
			"backtrace" : 4,
			"component" : "Unspecified",
			"destination" : "share/cmake/cppzmq",
			"paths" : 
			[
				"/home/carolina/Documentos/masters/1st_year/1st_semester/SDLE/project/g12/build/cppzmqConfig.cmake",
				"/home/carolina/Documentos/masters/1st_year/1st_semester/SDLE/project/g12/build/cppzmqConfigVersion.cmake"
			],
			"type" : "file"
		},
		{
			"backtrace" : 5,
			"component" : "Unspecified",
			"destination" : "share/cmake/cppzmq/libzmq-pkg-config",
			"paths" : 
			[
				"libzmq-pkg-config/FindZeroMQ.cmake"
			],
			"type" : "file"
		}
	],
	"paths" : 
	{
		"build" : ".",
		"source" : "."
	}
}
